mkdocs_quiz_plugin/__init__.py
mkdocs_quiz_plugin/quiz.py
mkdocs_quiz_plugin-0.1.0.dist-info/METADATA
mkdocs_quiz_plugin-0.1.0.dist-info/WHEEL
mkdocs_quiz_plugin-0.1.0.dist-info/entry_points.txt
mkdocs_quiz_plugin-0.1.0.dist-info/top_level.txt
mkdocs_quiz_plugin-0.1.0.dist-info/RECORD
